bionext_mcp/__init__.py
bionext_mcp/__main__.py
bionext_mcp/my_server.py
bionext_mcp-2.2.1.dist-info/METADATA
bionext_mcp-2.2.1.dist-info/WHEEL
bionext_mcp-2.2.1.dist-info/entry_points.txt
bionext_mcp-2.2.1.dist-info/licenses/LICENSE
bionext_mcp-2.2.1.dist-info/RECORD
