Metadata-Version: 2.4
Name: bionext-mcp
Version: 2.2.1
Summary: 🧬 生物信息学MCP服务器 - 专为ModelScope设计的智能生物数据分析工具
Project-URL: Homepage, https://github.com/Cherine0205/BioNext-mcp
Project-URL: Documentation, https://github.com/Cherine0205/BioNext-mcp#readme
Project-URL: Repository, https://github.com/Cherine0205/BioNext-mcp.git
Project-URL: Bug Tracker, https://github.com/Cherine0205/BioNext-mcp/issues
Author-email: BioNext Team <team@bionext.ai>
License: MIT
License-File: LICENSE
Keywords: MCP&Agent挑战赛,bioinformatics,genomics,mcp,modelscope,proteomics,python,single-cell
Classifier: Development Status :: 4 - Beta
Classifier: Intended Audience :: Science/Research
Classifier: License :: OSI Approved :: MIT License
Classifier: Programming Language :: Python :: 3
Classifier: Programming Language :: Python :: 3.8
Classifier: Programming Language :: Python :: 3.9
Classifier: Programming Language :: Python :: 3.10
Classifier: Programming Language :: Python :: 3.11
Classifier: Programming Language :: Python :: 3.12
Classifier: Topic :: Scientific/Engineering :: Bio-Informatics
Classifier: Topic :: Scientific/Engineering :: Information Analysis
Classifier: Topic :: Software Development :: Libraries :: Python Modules
Requires-Python: >=3.8
Requires-Dist: fastmcp>=0.1.0
Requires-Dist: pathlib2; python_version < '3.4'
